{"type": "FeatureCollection","features": [{"type":"Feature","geometry": {'type': 'Point', 'coordinates': [46.3738335, 13.0963233]},"properties": { "name": "AMARO PIAZZA MAGGIORE", "ph": "7.5 unità pH", "conducibilita": "659 µS/cm 20°C", "calcio": "98 mg/l Ca", "magnesio": "26 mg/l Mg", "durezza": "35 F", "fluoruri": "0.152 mg/L F", "nitrato": "3.22 mg/l NO3", "cloruro": "2.68 mg/l Cl", "solfato": "246 mg/l SO4", "sodio": "3 mg/l Na", "potassio": "< 1 mg/l K", "manganese": "< 5 µg/L Mn", "nitrito": "< 0.05 mg/l NO2", "ammoniaca": "< 0.05 mg/L NH4", "arsenico": "< 1 µg/L As", "residuo_fisso": "506 mg/l"}}]}